pyrallis/__init__.py
pyrallis/argparsing.py
pyrallis/cfgparsing.py
pyrallis/fields.py
pyrallis/help_formatter.py
pyrallis/options.py
pyrallis/py.typed
pyrallis/utils.py
pyrallis/parsers/__init__.py
pyrallis/parsers/config_parsers.py
pyrallis/parsers/decoding.py
pyrallis/parsers/encoding.py
pyrallis/parsers/registry_utils.py
pyrallis/wrappers/__init__.py
pyrallis/wrappers/dataclass_wrapper.py
pyrallis/wrappers/docstring.py
pyrallis/wrappers/field_metavar.py
pyrallis/wrappers/field_wrapper.py
pyrallis/wrappers/wrapper.py
pyrallis-0.3.1.dist-info/LICENSE
pyrallis-0.3.1.dist-info/METADATA
pyrallis-0.3.1.dist-info/WHEEL
pyrallis-0.3.1.dist-info/top_level.txt
pyrallis-0.3.1.dist-info/RECORD
