Metadata-Version: 2.1
Name: pyrallis
Version: 0.3.1
Summary: A framework for simple dataclass-based configurations.
Home-page: https://eladrich.github.io/pyrallis/
Author: Elad Richardson
License: UNKNOWN
Platform: UNKNOWN
Classifier: Programming Language :: Python :: 3
Classifier: License :: OSI Approved :: MIT License
Classifier: Operating System :: OS Independent
Requires-Python: >=3.6
License-File: LICENSE
Requires-Dist: typing-inspect
Requires-Dist: pyyaml
Requires-Dist: dataclasses ; python_version < "3.7"
